{
  "project": "it.wikipedia",
  "access": "all-access",
  "year": 2015,
  "week": 49,
  "start_date": "2015-11-30",
  "end_date": "2015-12-06",
  "days": [
    "2015-11-30",
    "2015-12-01",
    "2015-12-02",
    "2015-12-03",
    "2015-12-04",
    "2015-12-05",
    "2015-12-06"
  ],
  "total_articles": 2472,
  "articles": [
    {
      "rank": 1,
      "article": "Lucy_Maud_Montgomery",
      "views": 237289,
      "daily_views": [
        {
          "date": "2015-11-30",
          "views": 235410
        },
        {
          "date": "2015-12-01",
          "views": 1879
        },
        {
          "date": "2015-12-02",
          "views": 0
        },
        {
          "date": "2015-12-03",
          "views": 0
        },
        {
          "date": "2015-12-04",
          "views": 0
        },
        {
          "date": "2015-12-05",
          "views": 0
        },
        {
          "date": "2015-12-06",
          "views": 0
        }
      ],
      "google_news_url": "https://www.google.it/search?q=Lucy%20Maud%20Montgomery&hl=it&gl=it&authuser=0&source=lnt&tbs=cdr:1,cd_min:11/30/2015,cd_max:12/06/2015&tbm=nws",
      "pageviews_url": "https://pageviews.wmcloud.org/?project=it.wikipedia.org&platform=all-access&agent=user&redirects=0&start=2015-11-30&end=2015-12-06&pages=Lucy_Maud_Montgomery",
      "article_url": "https://it.wikipedia.org/wiki/Lucy_Maud_Montgomery",
      "description": "scrittrice canadese",
      "image_filename": "LMM_signed_photo.jpg",
      "image_url": "https://upload.wikimedia.org/wikipedia/commons/1/1d/LMM_signed_photo.jpg",
      "image_commons_url": "https://commons.wikimedia.org/wiki/File:LMM_signed_photo.jpg",
      "image_license": "Public domain",
      "image_copyrighted": "False"
    },
    {
      "rank": 2,
      "article": "Adele_(cantante)",
      "views": 155598,
      "daily_views": [
        {
          "date": "2015-11-30",
          "views": 11943
        },
        {
          "date": "2015-12-01",
          "views": 8592
        },
        {
          "date": "2015-12-02",
          "views": 7283
        },
        {
          "date": "2015-12-03",
          "views": 6693
        },
        {
          "date": "2015-12-04",
          "views": 6798
        },
        {
          "date": "2015-12-05",
          "views": 8158
        },
        {
          "date": "2015-12-06",
          "views": 106131
        }
      ],
      "google_news_url": "https://www.google.it/search?q=Adele%20%28cantante%29&hl=it&gl=it&authuser=0&source=lnt&tbs=cdr:1,cd_min:11/30/2015,cd_max:12/06/2015&tbm=nws",
      "pageviews_url": "https://pageviews.wmcloud.org/?project=it.wikipedia.org&platform=all-access&agent=user&redirects=0&start=2015-11-30&end=2015-12-06&pages=Adele_(cantante)",
      "article_url": "https://it.wikipedia.org/wiki/Adele_(cantante)",
      "description": "cantautrice e produttrice discografica britannica",
      "image_filename": "Adele_2016.jpg",
      "image_url": "https://upload.wikimedia.org/wikipedia/commons/thumb/7/7c/Adele_2016.jpg/1280px-Adele_2016.jpg",
      "image_commons_url": "https://commons.wikimedia.org/wiki/File:Adele_2016.jpg",
      "image_license": "CC BY 2.0",
      "image_copyrighted": "True"
    },
    {
      "rank": 3,
      "article": "Giubileo_universale_della_Chiesa_cattolica",
      "views": 92779,
      "daily_views": [
        {
          "date": "2015-11-30",
          "views": 12528
        },
        {
          "date": "2015-12-01",
          "views": 8127
        },
        {
          "date": "2015-12-02",
          "views": 9640
        },
        {
          "date": "2015-12-03",
          "views": 7923
        },
        {
          "date": "2015-12-04",
          "views": 16132
        },
        {
          "date": "2015-12-05",
          "views": 15663
        },
        {
          "date": "2015-12-06",
          "views": 22766
        }
      ],
      "google_news_url": "https://www.google.it/search?q=Giubileo%20universale%20della%20Chiesa%20cattolica&hl=it&gl=it&authuser=0&source=lnt&tbs=cdr:1,cd_min:11/30/2015,cd_max:12/06/2015&tbm=nws",
      "pageviews_url": "https://pageviews.wmcloud.org/?project=it.wikipedia.org&platform=all-access&agent=user&redirects=0&start=2015-11-30&end=2015-12-06&pages=Giubileo_universale_della_Chiesa_cattolica",
      "article_url": "https://it.wikipedia.org/wiki/Giubileo_universale_della_Chiesa_cattolica",
      "description": "celebrazione religiosa della Chiesa cattolica",
      "image_filename": "Giubileo_della_Redenzione_-_Apertura_della_Porta_Santa.jpg",
      "image_url": "https://upload.wikimedia.org/wikipedia/it/thumb/1/11/Giubileo_della_Redenzione_-_Apertura_della_Porta_Santa.jpg/1280px-Giubileo_della_Redenzione_-_Apertura_della_Porta_Santa.jpg",
      "image_commons_url": "https://commons.wikimedia.org/wiki/File:Giubileo_della_Redenzione_-_Apertura_della_Porta_Santa.jpg",
      "image_license": "",
      "image_copyrighted": ""
    },
    {
      "rank": 4,
      "article": "\u00c8_arrivata_la_felicit\u00e0_(serie_televisiva)",
      "views": 77334,
      "daily_views": [
        {
          "date": "2015-11-30",
          "views": 3095
        },
        {
          "date": "2015-12-01",
          "views": 16828
        },
        {
          "date": "2015-12-02",
          "views": 10596
        },
        {
          "date": "2015-12-03",
          "views": 24316
        },
        {
          "date": "2015-12-04",
          "views": 11902
        },
        {
          "date": "2015-12-05",
          "views": 6807
        },
        {
          "date": "2015-12-06",
          "views": 3790
        }
      ],
      "google_news_url": "https://www.google.it/search?q=%C3%88%20arrivata%20la%20felicit%C3%A0%20%28serie%20televisiva%29&hl=it&gl=it&authuser=0&source=lnt&tbs=cdr:1,cd_min:11/30/2015,cd_max:12/06/2015&tbm=nws",
      "pageviews_url": "https://pageviews.wmcloud.org/?project=it.wikipedia.org&platform=all-access&agent=user&redirects=0&start=2015-11-30&end=2015-12-06&pages=%C3%88_arrivata_la_felicit%C3%A0_(serie_televisiva)",
      "article_url": "https://it.wikipedia.org/wiki/%C3%88_arrivata_la_felicit%C3%A0_(serie_televisiva)",
      "description": "serie televisiva italiana",
      "image_filename": "\u00c8_arrivata_la_felicit\u00e0-screenshot_della_sigla.png",
      "image_url": "https://upload.wikimedia.org/wikipedia/it/thumb/2/26/%C3%88_arrivata_la_felicit%C3%A0-screenshot_della_sigla.png/1136px-%C3%88_arrivata_la_felicit%C3%A0-screenshot_della_sigla.png",
      "image_commons_url": "https://commons.wikimedia.org/wiki/File:%C3%88_arrivata_la_felicit%C3%A0-screenshot_della_sigla.png",
      "image_license": "",
      "image_copyrighted": ""
    },
    {
      "rank": 5,
      "article": "Guerre_stellari",
      "views": 74249,
      "daily_views": [
        {
          "date": "2015-11-30",
          "views": 9320
        },
        {
          "date": "2015-12-01",
          "views": 8933
        },
        {
          "date": "2015-12-02",
          "views": 9014
        },
        {
          "date": "2015-12-03",
          "views": 9079
        },
        {
          "date": "2015-12-04",
          "views": 9142
        },
        {
          "date": "2015-12-05",
          "views": 11953
        },
        {
          "date": "2015-12-06",
          "views": 16808
        }
      ],
      "google_news_url": "https://www.google.it/search?q=Guerre%20stellari&hl=it&gl=it&authuser=0&source=lnt&tbs=cdr:1,cd_min:11/30/2015,cd_max:12/06/2015&tbm=nws",
      "pageviews_url": "https://pageviews.wmcloud.org/?project=it.wikipedia.org&platform=all-access&agent=user&redirects=0&start=2015-11-30&end=2015-12-06&pages=Guerre_stellari",
      "article_url": "https://it.wikipedia.org/wiki/Guerre_stellari",
      "description": "franchise creato da George Lucas",
      "image_filename": "Star_Wars_Logo.svg",
      "image_url": "https://upload.wikimedia.org/wikipedia/commons/thumb/6/6c/Star_Wars_Logo.svg/1280px-Star_Wars_Logo.svg.png",
      "image_commons_url": "https://commons.wikimedia.org/wiki/File:Star_Wars_Logo.svg",
      "image_license": "Public domain",
      "image_copyrighted": "False"
    },
    {
      "rank": 6,
      "article": "Anna_dai_capelli_rossi_(romanzo)",
      "views": 68920,
      "daily_views": [
        {
          "date": "2015-11-30",
          "views": 67904
        },
        {
          "date": "2015-12-01",
          "views": 1016
        },
        {
          "date": "2015-12-02",
          "views": 0
        },
        {
          "date": "2015-12-03",
          "views": 0
        },
        {
          "date": "2015-12-04",
          "views": 0
        },
        {
          "date": "2015-12-05",
          "views": 0
        },
        {
          "date": "2015-12-06",
          "views": 0
        }
      ],
      "google_news_url": "https://www.google.it/search?q=Anna%20dai%20capelli%20rossi%20%28romanzo%29&hl=it&gl=it&authuser=0&source=lnt&tbs=cdr:1,cd_min:11/30/2015,cd_max:12/06/2015&tbm=nws",
      "pageviews_url": "https://pageviews.wmcloud.org/?project=it.wikipedia.org&platform=all-access&agent=user&redirects=0&start=2015-11-30&end=2015-12-06&pages=Anna_dai_capelli_rossi_(romanzo)",
      "article_url": "https://it.wikipedia.org/wiki/Anna_dai_capelli_rossi_(romanzo)",
      "description": "romanzo di Lucy Maud Montgomery",
      "image_filename": "Montgomery_Anne_of_Green_Gables.jpg",
      "image_url": "https://upload.wikimedia.org/wikipedia/commons/8/8b/Montgomery_Anne_of_Green_Gables.jpg",
      "image_commons_url": "https://commons.wikimedia.org/wiki/File:Montgomery_Anne_of_Green_Gables.jpg",
      "image_license": "Public domain",
      "image_copyrighted": "False"
    },
    {
      "rank": 7,
      "article": "Jonah_Lomu",
      "views": 68586,
      "daily_views": [
        {
          "date": "2015-11-30",
          "views": 40630
        },
        {
          "date": "2015-12-01",
          "views": 17913
        },
        {
          "date": "2015-12-02",
          "views": 4486
        },
        {
          "date": "2015-12-03",
          "views": 1917
        },
        {
          "date": "2015-12-04",
          "views": 1244
        },
        {
          "date": "2015-12-05",
          "views": 1277
        },
        {
          "date": "2015-12-06",
          "views": 1119
        }
      ],
      "google_news_url": "https://www.google.it/search?q=Jonah%20Lomu&hl=it&gl=it&authuser=0&source=lnt&tbs=cdr:1,cd_min:11/30/2015,cd_max:12/06/2015&tbm=nws",
      "pageviews_url": "https://pageviews.wmcloud.org/?project=it.wikipedia.org&platform=all-access&agent=user&redirects=0&start=2015-11-30&end=2015-12-06&pages=Jonah_Lomu",
      "article_url": "https://it.wikipedia.org/wiki/Jonah_Lomu",
      "description": "rugbista a 15 neozelandese",
      "image_filename": "Jonah_Lomu_(cropped).jpg",
      "image_url": "https://upload.wikimedia.org/wikipedia/commons/c/c6/Jonah_Lomu_%28cropped%29.jpg",
      "image_commons_url": "https://commons.wikimedia.org/wiki/File:Jonah_Lomu_(cropped).jpg",
      "image_license": "CC BY-SA 2.0",
      "image_copyrighted": "True"
    },
    {
      "rank": 8,
      "article": "The_Walking_Dead_(serie_televisiva)",
      "views": 63582,
      "daily_views": [
        {
          "date": "2015-11-30",
          "views": 14108
        },
        {
          "date": "2015-12-01",
          "views": 14803
        },
        {
          "date": "2015-12-02",
          "views": 9070
        },
        {
          "date": "2015-12-03",
          "views": 6935
        },
        {
          "date": "2015-12-04",
          "views": 5830
        },
        {
          "date": "2015-12-05",
          "views": 5577
        },
        {
          "date": "2015-12-06",
          "views": 7259
        }
      ],
      "google_news_url": "https://www.google.it/search?q=The%20Walking%20Dead%20%28serie%20televisiva%29&hl=it&gl=it&authuser=0&source=lnt&tbs=cdr:1,cd_min:11/30/2015,cd_max:12/06/2015&tbm=nws",
      "pageviews_url": "https://pageviews.wmcloud.org/?project=it.wikipedia.org&platform=all-access&agent=user&redirects=0&start=2015-11-30&end=2015-12-06&pages=The_Walking_Dead_(serie_televisiva)",
      "article_url": "https://it.wikipedia.org/wiki/The_Walking_Dead_(serie_televisiva)",
      "description": "serie televisiva statunitense (2010-2022)",
      "image_filename": "",
      "image_url": "",
      "image_commons_url": "",
      "image_license": "",
      "image_copyrighted": ""
    },
    {
      "rank": 9,
      "article": "Kobe_Bryant",
      "views": 55799,
      "daily_views": [
        {
          "date": "2015-11-30",
          "views": 27843
        },
        {
          "date": "2015-12-01",
          "views": 10375
        },
        {
          "date": "2015-12-02",
          "views": 8569
        },
        {
          "date": "2015-12-03",
          "views": 3573
        },
        {
          "date": "2015-12-04",
          "views": 1932
        },
        {
          "date": "2015-12-05",
          "views": 1588
        },
        {
          "date": "2015-12-06",
          "views": 1919
        }
      ],
      "google_news_url": "https://www.google.it/search?q=Kobe%20Bryant&hl=it&gl=it&authuser=0&source=lnt&tbs=cdr:1,cd_min:11/30/2015,cd_max:12/06/2015&tbm=nws",
      "pageviews_url": "https://pageviews.wmcloud.org/?project=it.wikipedia.org&platform=all-access&agent=user&redirects=0&start=2015-11-30&end=2015-12-06&pages=Kobe_Bryant",
      "article_url": "https://it.wikipedia.org/wiki/Kobe_Bryant",
      "description": "cestista statunitense (1978-2020)",
      "image_filename": "KBryant8.jpg",
      "image_url": "https://upload.wikimedia.org/wikipedia/commons/2/22/KBryant8.jpg",
      "image_commons_url": "https://commons.wikimedia.org/wiki/File:KBryant8.jpg",
      "image_license": "Public domain",
      "image_copyrighted": "False"
    },
    {
      "rank": 10,
      "article": "Stato_Islamico",
      "views": 55405,
      "daily_views": [
        {
          "date": "2015-11-30",
          "views": 9497
        },
        {
          "date": "2015-12-01",
          "views": 9428
        },
        {
          "date": "2015-12-02",
          "views": 9267
        },
        {
          "date": "2015-12-03",
          "views": 8644
        },
        {
          "date": "2015-12-04",
          "views": 7770
        },
        {
          "date": "2015-12-05",
          "views": 5670
        },
        {
          "date": "2015-12-06",
          "views": 5129
        }
      ],
      "google_news_url": "https://www.google.it/search?q=Stato%20Islamico&hl=it&gl=it&authuser=0&source=lnt&tbs=cdr:1,cd_min:11/30/2015,cd_max:12/06/2015&tbm=nws",
      "pageviews_url": "https://pageviews.wmcloud.org/?project=it.wikipedia.org&platform=all-access&agent=user&redirects=0&start=2015-11-30&end=2015-12-06&pages=Stato_Islamico",
      "article_url": "https://it.wikipedia.org/wiki/Stato_Islamico",
      "description": "",
      "image_filename": "",
      "image_url": "",
      "image_commons_url": "",
      "image_license": "",
      "image_copyrighted": ""
    },
    {
      "rank": 11,
      "article": "Gonzalo_Higua\u00edn",
      "views": 54727,
      "daily_views": [
        {
          "date": "2015-11-30",
          "views": 13097
        },
        {
          "date": "2015-12-01",
          "views": 16609
        },
        {
          "date": "2015-12-02",
          "views": 6393
        },
        {
          "date": "2015-12-03",
          "views": 3363
        },
        {
          "date": "2015-12-04",
          "views": 3489
        },
        {
          "date": "2015-12-05",
          "views": 3499
        },
        {
          "date": "2015-12-06",
          "views": 8277
        }
      ],
      "google_news_url": "https://www.google.it/search?q=Gonzalo%20Higua%C3%ADn&hl=it&gl=it&authuser=0&source=lnt&tbs=cdr:1,cd_min:11/30/2015,cd_max:12/06/2015&tbm=nws",
      "pageviews_url": "https://pageviews.wmcloud.org/?project=it.wikipedia.org&platform=all-access&agent=user&redirects=0&start=2015-11-30&end=2015-12-06&pages=Gonzalo_Higua%C3%ADn",
      "article_url": "https://it.wikipedia.org/wiki/Gonzalo_Higua%C3%ADn",
      "description": "calciatore argentino (1987-)",
      "image_filename": "Higua\u00edn_20180626.jpg",
      "image_url": "https://upload.wikimedia.org/wikipedia/commons/f/fe/Higua%C3%ADn_20180626.jpg",
      "image_commons_url": "https://commons.wikimedia.org/wiki/File:Higua%C3%ADn_20180626.jpg",
      "image_license": "CC BY-SA 3.0",
      "image_copyrighted": "True"
    },
    {
      "rank": 12,
      "article": "Grey's_Anatomy",
      "views": 54272,
      "daily_views": [
        {
          "date": "2015-11-30",
          "views": 13057
        },
        {
          "date": "2015-12-01",
          "views": 10326
        },
        {
          "date": "2015-12-02",
          "views": 7177
        },
        {
          "date": "2015-12-03",
          "views": 6765
        },
        {
          "date": "2015-12-04",
          "views": 6372
        },
        {
          "date": "2015-12-05",
          "views": 4880
        },
        {
          "date": "2015-12-06",
          "views": 5695
        }
      ],
      "google_news_url": "https://www.google.it/search?q=Grey%27s%20Anatomy&hl=it&gl=it&authuser=0&source=lnt&tbs=cdr:1,cd_min:11/30/2015,cd_max:12/06/2015&tbm=nws",
      "pageviews_url": "https://pageviews.wmcloud.org/?project=it.wikipedia.org&platform=all-access&agent=user&redirects=0&start=2015-11-30&end=2015-12-06&pages=Grey%27s_Anatomy",
      "article_url": "https://it.wikipedia.org/wiki/Grey%27s_Anatomy",
      "description": "serie televisiva statunitense del 2005",
      "image_filename": "",
      "image_url": "",
      "image_commons_url": "",
      "image_license": "",
      "image_copyrighted": ""
    },
    {
      "rank": 13,
      "article": "Vladimir_Putin",
      "views": 53553,
      "daily_views": [
        {
          "date": "2015-11-30",
          "views": 5454
        },
        {
          "date": "2015-12-01",
          "views": 5665
        },
        {
          "date": "2015-12-02",
          "views": 6053
        },
        {
          "date": "2015-12-03",
          "views": 9112
        },
        {
          "date": "2015-12-04",
          "views": 11300
        },
        {
          "date": "2015-12-05",
          "views": 7336
        },
        {
          "date": "2015-12-06",
          "views": 8633
        }
      ],
      "google_news_url": "https://www.google.it/search?q=Vladimir%20Putin&hl=it&gl=it&authuser=0&source=lnt&tbs=cdr:1,cd_min:11/30/2015,cd_max:12/06/2015&tbm=nws",
      "pageviews_url": "https://pageviews.wmcloud.org/?project=it.wikipedia.org&platform=all-access&agent=user&redirects=0&start=2015-11-30&end=2015-12-06&pages=Vladimir_Putin",
      "article_url": "https://it.wikipedia.org/wiki/Vladimir_Putin",
      "description": "politico e agente segreto russo, funzionario del KGB e presidente della Federazione Russa (2000\u20132008, 2012\u2013oggi)",
      "image_filename": "\u0412\u043b\u0430\u0434\u0438\u043c\u0438\u0440_\u041f\u0443\u0442\u0438\u043d_(2025-09-30).jpg",
      "image_url": "https://upload.wikimedia.org/wikipedia/commons/0/04/%D0%92%D0%BB%D0%B0%D0%B4%D0%B8%D0%BC%D0%B8%D1%80_%D0%9F%D1%83%D1%82%D0%B8%D0%BD_%282025-09-30%29.jpg",
      "image_commons_url": "https://commons.wikimedia.org/wiki/File:%D0%92%D0%BB%D0%B0%D0%B4%D0%B8%D0%BC%D0%B8%D1%80_%D0%9F%D1%83%D1%82%D0%B8%D0%BD_(2025-09-30).jpg",
      "image_license": "CC BY 4.0",
      "image_copyrighted": "True"
    },
    {
      "rank": 14,
      "article": "Star_Wars:_Il_risveglio_della_Forza",
      "views": 52061,
      "daily_views": [
        {
          "date": "2015-11-30",
          "views": 6387
        },
        {
          "date": "2015-12-01",
          "views": 6609
        },
        {
          "date": "2015-12-02",
          "views": 6611
        },
        {
          "date": "2015-12-03",
          "views": 6493
        },
        {
          "date": "2015-12-04",
          "views": 6536
        },
        {
          "date": "2015-12-05",
          "views": 8055
        },
        {
          "date": "2015-12-06",
          "views": 11370
        }
      ],
      "google_news_url": "https://www.google.it/search?q=Star%20Wars%3A%20Il%20risveglio%20della%20Forza&hl=it&gl=it&authuser=0&source=lnt&tbs=cdr:1,cd_min:11/30/2015,cd_max:12/06/2015&tbm=nws",
      "pageviews_url": "https://pageviews.wmcloud.org/?project=it.wikipedia.org&platform=all-access&agent=user&redirects=0&start=2015-11-30&end=2015-12-06&pages=Star_Wars%3A_Il_risveglio_della_Forza",
      "article_url": "https://it.wikipedia.org/wiki/Star_Wars%3A_Il_risveglio_della_Forza",
      "description": "",
      "image_filename": "",
      "image_url": "",
      "image_commons_url": "",
      "image_license": "",
      "image_copyrighted": ""
    },
    {
      "rank": 15,
      "article": "Quantico_(serie_televisiva)",
      "views": 49744,
      "daily_views": [
        {
          "date": "2015-11-30",
          "views": 6882
        },
        {
          "date": "2015-12-01",
          "views": 5567
        },
        {
          "date": "2015-12-02",
          "views": 11772
        },
        {
          "date": "2015-12-03",
          "views": 9325
        },
        {
          "date": "2015-12-04",
          "views": 5566
        },
        {
          "date": "2015-12-05",
          "views": 5022
        },
        {
          "date": "2015-12-06",
          "views": 5610
        }
      ],
      "google_news_url": "https://www.google.it/search?q=Quantico%20%28serie%20televisiva%29&hl=it&gl=it&authuser=0&source=lnt&tbs=cdr:1,cd_min:11/30/2015,cd_max:12/06/2015&tbm=nws",
      "pageviews_url": "https://pageviews.wmcloud.org/?project=it.wikipedia.org&platform=all-access&agent=user&redirects=0&start=2015-11-30&end=2015-12-06&pages=Quantico_(serie_televisiva)",
      "article_url": "https://it.wikipedia.org/wiki/Quantico_(serie_televisiva)",
      "description": "serie televisiva statunitense",
      "image_filename": "Quantico_serie_TV.jpg",
      "image_url": "https://upload.wikimedia.org/wikipedia/it/c/c2/Quantico_serie_TV.jpg",
      "image_commons_url": "https://commons.wikimedia.org/wiki/File:Quantico_serie_TV.jpg",
      "image_license": "",
      "image_copyrighted": ""
    },
    {
      "rank": 16,
      "article": "Coppa_Italia_2015-2016",
      "views": 48994,
      "daily_views": [
        {
          "date": "2015-11-30",
          "views": 3471
        },
        {
          "date": "2015-12-01",
          "views": 13037
        },
        {
          "date": "2015-12-02",
          "views": 15964
        },
        {
          "date": "2015-12-03",
          "views": 9280
        },
        {
          "date": "2015-12-04",
          "views": 4640
        },
        {
          "date": "2015-12-05",
          "views": 1380
        },
        {
          "date": "2015-12-06",
          "views": 1222
        }
      ],
      "google_news_url": "https://www.google.it/search?q=Coppa%20Italia%202015-2016&hl=it&gl=it&authuser=0&source=lnt&tbs=cdr:1,cd_min:11/30/2015,cd_max:12/06/2015&tbm=nws",
      "pageviews_url": "https://pageviews.wmcloud.org/?project=it.wikipedia.org&platform=all-access&agent=user&redirects=0&start=2015-11-30&end=2015-12-06&pages=Coppa_Italia_2015-2016",
      "article_url": "https://it.wikipedia.org/wiki/Coppa_Italia_2015-2016",
      "description": "69\u00aa edizione della Coppa Italia",
      "image_filename": "Juventus_Coppa_Italia_2016.jpg",
      "image_url": "https://upload.wikimedia.org/wikipedia/commons/thumb/b/b0/Juventus_Coppa_Italia_2016.jpg/1280px-Juventus_Coppa_Italia_2016.jpg",
      "image_commons_url": "https://commons.wikimedia.org/wiki/File:Juventus_Coppa_Italia_2016.jpg",
      "image_license": "Attribution",
      "image_copyrighted": ""
    },
    {
      "rank": 17,
      "article": "Italia",
      "views": 47523,
      "daily_views": [
        {
          "date": "2015-11-30",
          "views": 7690
        },
        {
          "date": "2015-12-01",
          "views": 7114
        },
        {
          "date": "2015-12-02",
          "views": 6957
        },
        {
          "date": "2015-12-03",
          "views": 6943
        },
        {
          "date": "2015-12-04",
          "views": 6116
        },
        {
          "date": "2015-12-05",
          "views": 5936
        },
        {
          "date": "2015-12-06",
          "views": 6767
        }
      ],
      "google_news_url": "https://www.google.it/search?q=Italia&hl=it&gl=it&authuser=0&source=lnt&tbs=cdr:1,cd_min:11/30/2015,cd_max:12/06/2015&tbm=nws",
      "pageviews_url": "https://pageviews.wmcloud.org/?project=it.wikipedia.org&platform=all-access&agent=user&redirects=0&start=2015-11-30&end=2015-12-06&pages=Italia",
      "article_url": "https://it.wikipedia.org/wiki/Italia",
      "description": "stato dell'Europa meridionale, membro dell'Unione europea",
      "image_filename": "Flag_of_Italy.svg",
      "image_url": "https://upload.wikimedia.org/wikipedia/commons/thumb/0/03/Flag_of_Italy.svg/1280px-Flag_of_Italy.svg.png",
      "image_commons_url": "https://commons.wikimedia.org/wiki/File:Flag_of_Italy.svg",
      "image_license": "Public domain",
      "image_copyrighted": "False"
    },
    {
      "rank": 18,
      "article": "Episodi_di_The_Walking_Dead_(sesta_stagione)",
      "views": 44058,
      "daily_views": [
        {
          "date": "2015-11-30",
          "views": 10299
        },
        {
          "date": "2015-12-01",
          "views": 11701
        },
        {
          "date": "2015-12-02",
          "views": 6587
        },
        {
          "date": "2015-12-03",
          "views": 4430
        },
        {
          "date": "2015-12-04",
          "views": 3660
        },
        {
          "date": "2015-12-05",
          "views": 3426
        },
        {
          "date": "2015-12-06",
          "views": 3955
        }
      ],
      "google_news_url": "https://www.google.it/search?q=Episodi%20di%20The%20Walking%20Dead%20%28sesta%20stagione%29&hl=it&gl=it&authuser=0&source=lnt&tbs=cdr:1,cd_min:11/30/2015,cd_max:12/06/2015&tbm=nws",
      "pageviews_url": "https://pageviews.wmcloud.org/?project=it.wikipedia.org&platform=all-access&agent=user&redirects=0&start=2015-11-30&end=2015-12-06&pages=Episodi_di_The_Walking_Dead_(sesta_stagione)",
      "article_url": "https://it.wikipedia.org/wiki/Episodi_di_The_Walking_Dead_(sesta_stagione)",
      "description": "stagione televisiva",
      "image_filename": "",
      "image_url": "",
      "image_commons_url": "",
      "image_license": "",
      "image_copyrighted": ""
    },
    {
      "rank": 19,
      "article": "The_Big_Bang_Theory",
      "views": 42058,
      "daily_views": [
        {
          "date": "2015-11-30",
          "views": 6256
        },
        {
          "date": "2015-12-01",
          "views": 6595
        },
        {
          "date": "2015-12-02",
          "views": 7074
        },
        {
          "date": "2015-12-03",
          "views": 6714
        },
        {
          "date": "2015-12-04",
          "views": 5922
        },
        {
          "date": "2015-12-05",
          "views": 4810
        },
        {
          "date": "2015-12-06",
          "views": 4687
        }
      ],
      "google_news_url": "https://www.google.it/search?q=The%20Big%20Bang%20Theory&hl=it&gl=it&authuser=0&source=lnt&tbs=cdr:1,cd_min:11/30/2015,cd_max:12/06/2015&tbm=nws",
      "pageviews_url": "https://pageviews.wmcloud.org/?project=it.wikipedia.org&platform=all-access&agent=user&redirects=0&start=2015-11-30&end=2015-12-06&pages=The_Big_Bang_Theory",
      "article_url": "https://it.wikipedia.org/wiki/The_Big_Bang_Theory",
      "description": "serie televisiva statunitense (2007-2019)",
      "image_filename": "TBBT_logo.svg",
      "image_url": "https://upload.wikimedia.org/wikipedia/commons/thumb/1/13/TBBT_logo.svg/1280px-TBBT_logo.svg.png",
      "image_commons_url": "https://commons.wikimedia.org/wiki/File:TBBT_logo.svg",
      "image_license": "Public domain",
      "image_copyrighted": "False"
    },
    {
      "rank": 20,
      "article": "Scott_Weiland",
      "views": 41191,
      "daily_views": [
        {
          "date": "2015-11-30",
          "views": 0
        },
        {
          "date": "2015-12-01",
          "views": 0
        },
        {
          "date": "2015-12-02",
          "views": 0
        },
        {
          "date": "2015-12-03",
          "views": 0
        },
        {
          "date": "2015-12-04",
          "views": 31607
        },
        {
          "date": "2015-12-05",
          "views": 7022
        },
        {
          "date": "2015-12-06",
          "views": 2562
        }
      ],
      "google_news_url": "https://www.google.it/search?q=Scott%20Weiland&hl=it&gl=it&authuser=0&source=lnt&tbs=cdr:1,cd_min:11/30/2015,cd_max:12/06/2015&tbm=nws",
      "pageviews_url": "https://pageviews.wmcloud.org/?project=it.wikipedia.org&platform=all-access&agent=user&redirects=0&start=2015-11-30&end=2015-12-06&pages=Scott_Weiland",
      "article_url": "https://it.wikipedia.org/wiki/Scott_Weiland",
      "description": "cantante statunitense",
      "image_filename": "Scott_Weiland_(Stone_Temple_Pilots)_Open_Air_St._Gallen_(rotated).jpg",
      "image_url": "https://upload.wikimedia.org/wikipedia/commons/3/36/Scott_Weiland_%28Stone_Temple_Pilots%29_Open_Air_St._Gallen_%28rotated%29.jpg",
      "image_commons_url": "https://commons.wikimedia.org/wiki/File:Scott_Weiland_(Stone_Temple_Pilots)_Open_Air_St._Gallen_(rotated).jpg",
      "image_license": "CC BY-SA 3.0",
      "image_copyrighted": "True"
    },
    {
      "rank": 21,
      "article": "Immacolata_Concezione",
      "views": 41029,
      "daily_views": [
        {
          "date": "2015-11-30",
          "views": 3353
        },
        {
          "date": "2015-12-01",
          "views": 3949
        },
        {
          "date": "2015-12-02",
          "views": 4450
        },
        {
          "date": "2015-12-03",
          "views": 5190
        },
        {
          "date": "2015-12-04",
          "views": 8113
        },
        {
          "date": "2015-12-05",
          "views": 6936
        },
        {
          "date": "2015-12-06",
          "views": 9038
        }
      ],
      "google_news_url": "https://www.google.it/search?q=Immacolata%20Concezione&hl=it&gl=it&authuser=0&source=lnt&tbs=cdr:1,cd_min:11/30/2015,cd_max:12/06/2015&tbm=nws",
      "pageviews_url": "https://pageviews.wmcloud.org/?project=it.wikipedia.org&platform=all-access&agent=user&redirects=0&start=2015-11-30&end=2015-12-06&pages=Immacolata_Concezione",
      "article_url": "https://it.wikipedia.org/wiki/Immacolata_Concezione",
      "description": "dogma cattolico secondo cui la Vergine Maria \u00e8 stata concepita senza peccato originale",
      "image_filename": "Imaculada_-_Murillo.jpg",
      "image_url": "https://upload.wikimedia.org/wikipedia/commons/thumb/0/0b/Imaculada_-_Murillo.jpg/1280px-Imaculada_-_Murillo.jpg",
      "image_commons_url": "https://commons.wikimedia.org/wiki/File:Imaculada_-_Murillo.jpg",
      "image_license": "Public domain",
      "image_copyrighted": "False"
    },
    {
      "rank": 22,
      "article": "The_Vampire_Diaries",
      "views": 40886,
      "daily_views": [
        {
          "date": "2015-11-30",
          "views": 5711
        },
        {
          "date": "2015-12-01",
          "views": 8026
        },
        {
          "date": "2015-12-02",
          "views": 5798
        },
        {
          "date": "2015-12-03",
          "views": 4988
        },
        {
          "date": "2015-12-04",
          "views": 6419
        },
        {
          "date": "2015-12-05",
          "views": 4434
        },
        {
          "date": "2015-12-06",
          "views": 5510
        }
      ],
      "google_news_url": "https://www.google.it/search?q=The%20Vampire%20Diaries&hl=it&gl=it&authuser=0&source=lnt&tbs=cdr:1,cd_min:11/30/2015,cd_max:12/06/2015&tbm=nws",
      "pageviews_url": "https://pageviews.wmcloud.org/?project=it.wikipedia.org&platform=all-access&agent=user&redirects=0&start=2015-11-30&end=2015-12-06&pages=The_Vampire_Diaries",
      "article_url": "https://it.wikipedia.org/wiki/The_Vampire_Diaries",
      "description": "serie televisiva statunitense (2009-2017)",
      "image_filename": "",
      "image_url": "",
      "image_commons_url": "",
      "image_license": "",
      "image_copyrighted": ""
    },
    {
      "rank": 23,
      "article": "Santa_Barbara",
      "views": 40347,
      "daily_views": [
        {
          "date": "2015-11-30",
          "views": 0
        },
        {
          "date": "2015-12-01",
          "views": 1218
        },
        {
          "date": "2015-12-02",
          "views": 1820
        },
        {
          "date": "2015-12-03",
          "views": 5391
        },
        {
          "date": "2015-12-04",
          "views": 26904
        },
        {
          "date": "2015-12-05",
          "views": 3331
        },
        {
          "date": "2015-12-06",
          "views": 1683
        }
      ],
      "google_news_url": "https://www.google.it/search?q=Santa%20Barbara&hl=it&gl=it&authuser=0&source=lnt&tbs=cdr:1,cd_min:11/30/2015,cd_max:12/06/2015&tbm=nws",
      "pageviews_url": "https://pageviews.wmcloud.org/?project=it.wikipedia.org&platform=all-access&agent=user&redirects=0&start=2015-11-30&end=2015-12-06&pages=Santa_Barbara",
      "article_url": "https://it.wikipedia.org/wiki/Santa_Barbara",
      "description": "martire cristiana",
      "image_filename": "Santa_Barbara_(Patern\u00f2).jpg",
      "image_url": "https://upload.wikimedia.org/wikipedia/commons/thumb/6/64/Santa_Barbara_%28Patern%C3%B2%29.jpg/1280px-Santa_Barbara_%28Patern%C3%B2%29.jpg",
      "image_commons_url": "https://commons.wikimedia.org/wiki/File:Santa_Barbara_(Patern%C3%B2).jpg",
      "image_license": "Public domain",
      "image_copyrighted": "False"
    },
    {
      "rank": 24,
      "article": "Luca_De_Filippo",
      "views": 40233,
      "daily_views": [
        {
          "date": "2015-11-30",
          "views": 22115
        },
        {
          "date": "2015-12-01",
          "views": 9675
        },
        {
          "date": "2015-12-02",
          "views": 2891
        },
        {
          "date": "2015-12-03",
          "views": 1627
        },
        {
          "date": "2015-12-04",
          "views": 1375
        },
        {
          "date": "2015-12-05",
          "views": 1463
        },
        {
          "date": "2015-12-06",
          "views": 1087
        }
      ],
      "google_news_url": "https://www.google.it/search?q=Luca%20De%20Filippo&hl=it&gl=it&authuser=0&source=lnt&tbs=cdr:1,cd_min:11/30/2015,cd_max:12/06/2015&tbm=nws",
      "pageviews_url": "https://pageviews.wmcloud.org/?project=it.wikipedia.org&platform=all-access&agent=user&redirects=0&start=2015-11-30&end=2015-12-06&pages=Luca_De_Filippo",
      "article_url": "https://it.wikipedia.org/wiki/Luca_De_Filippo",
      "description": "attore e regista teatrale italiano (1948-2015)",
      "image_filename": "Luca_De_FilippoNazionale.jpg",
      "image_url": "https://upload.wikimedia.org/wikipedia/commons/thumb/e/e9/Luca_De_FilippoNazionale.jpg/1280px-Luca_De_FilippoNazionale.jpg",
      "image_commons_url": "https://commons.wikimedia.org/wiki/File:Luca_De_FilippoNazionale.jpg",
      "image_license": "CC BY-SA 4.0",
      "image_copyrighted": "True"
    },
    {
      "rank": 25,
      "article": "The_Visit_(film_2015)",
      "views": 39265,
      "daily_views": [
        {
          "date": "2015-11-30",
          "views": 6748
        },
        {
          "date": "2015-12-01",
          "views": 5576
        },
        {
          "date": "2015-12-02",
          "views": 5260
        },
        {
          "date": "2015-12-03",
          "views": 4218
        },
        {
          "date": "2015-12-04",
          "views": 4261
        },
        {
          "date": "2015-12-05",
          "views": 6274
        },
        {
          "date": "2015-12-06",
          "views": 6928
        }
      ],
      "google_news_url": "https://www.google.it/search?q=The%20Visit%20%28film%202015%29&hl=it&gl=it&authuser=0&source=lnt&tbs=cdr:1,cd_min:11/30/2015,cd_max:12/06/2015&tbm=nws",
      "pageviews_url": "https://pageviews.wmcloud.org/?project=it.wikipedia.org&platform=all-access&agent=user&redirects=0&start=2015-11-30&end=2015-12-06&pages=The_Visit_(film_2015)",
      "article_url": "https://it.wikipedia.org/wiki/The_Visit_(film_2015)",
      "description": "film del 2015 diretto da M. Night Shyamalan",
      "image_filename": "The_Visit.png",
      "image_url": "https://upload.wikimedia.org/wikipedia/it/thumb/6/6b/The_Visit.png/1280px-The_Visit.png",
      "image_commons_url": "https://commons.wikimedia.org/wiki/File:The_Visit.png",
      "image_license": "",
      "image_copyrighted": ""
    }
  ]
}
